nebulaai_memory_agents/__init__.py
nebulaai_memory_agents/cli.py
nebulaai_memory_agents/sdk.py
nebulaai_memory_agents-0.1.0.dist-info/METADATA
nebulaai_memory_agents-0.1.0.dist-info/WHEEL
nebulaai_memory_agents-0.1.0.dist-info/entry_points.txt
nebulaai_memory_agents-0.1.0.dist-info/top_level.txt
nebulaai_memory_agents-0.1.0.dist-info/RECORD
